mozpy/__init__.py
mozpy/moz.py
mozpy-0.0.8.data/scripts/mozprinter
src/__init__.py
src/mozpy/__init__.py
src/mozpy/moz.py
mozpy-0.0.8.dist-info/METADATA
mozpy-0.0.8.dist-info/WHEEL
mozpy-0.0.8.dist-info/top_level.txt
mozpy-0.0.8.dist-info/RECORD
