Metadata-Version: 2.1
Name: mozpy
Version: 0.0.8
Summary: a veri useful package for programming moz like
Requires-Dist: colorama
